USAGE.md
ee_cli/__init__.py
ee_cli/constants.py
ee_cli/main.py
ee_cli/repl_content_state.py
ee_cli/settings.py
ee_cli/ui.py
ee_cli/utils.py
ee_cli-1.1.3.dist-info/entry_points.txt
ee_cli-1.1.3.dist-info/LICENSE
ee_cli-1.1.3.dist-info/WHEEL
ee_cli-1.1.3.dist-info/METADATA
ee_cli-1.1.3.dist-info/RECORD
