Metadata-Version: 2.1
Name: ee-cli
Version: 1.1.3
Summary: A salve for timesmiths
Author: Ainsley
Author-email: mcgrath.ainsley@gmail.com
Requires-Python: >=3.6.1,<4.0.0
Classifier: Programming Language :: Python :: 3
Classifier: Programming Language :: Python :: 3.10
Classifier: Programming Language :: Python :: 3.7
Classifier: Programming Language :: Python :: 3.8
Classifier: Programming Language :: Python :: 3.9
Requires-Dist: pendulum (>=2.1.2,<3.0.0)
Requires-Dist: pydantic (>=1.6.1,<2.0.0)
Requires-Dist: pyperclip (>=1.8.0,<2.0.0)
Requires-Dist: typer (>=0.3.2,<0.4.0)
